{
  "data": {
    "props": {
      "body": "Lorem ipsum dolor sit amet consectetur adipisicing elit. Velit facilis asperiores porro quaerat doloribus, eveniet dolore. Adipisci tempora aut inventore optio animi., tempore temporibus quo laudantium.",
      "imgSrc": "https://images.unsplash.com/photo-1496128858413-b36217c2ce36?ixlib=rb-1.2.1&ixqx=exTPH5Vqg4&ixid=eyJhcHBfaWQiOjEyMDd9&auto=format&fit=crop&w=1679&q=80",
      "label": "Article",
      "title": "Boost your conversion rate now!"
    },
    "slots": {
      "children": [
        {
          "type": "template-demo",
          "demoId": "gsI4PO5HfP",
          "patternId": "author",
          "templateId": "react"
        },
        {
          "type": "template-demo",
          "demoId": "2ysfvm4ShE",
          "patternId": "button",
          "templateId": "react"
        }
      ]
    }
  },
  "description": "",
  "height": 621,
  "id": "RN96ZpJJpY",
  "patternId": "card",
  "templateId": "react",
  "title": "One Author CTA",
  "type": "data",
  "width": 336,
  "theme": {
    "Dual": "light"
  }
}
