{
  "id": "k6cLoOVIX",
  "data": {
    "content": {
      "type": "doc",
      "content": [
        {
          "type": "heading",
          "attrs": {
            "level": 1,
            "textAlign": "left"
          },
          "content": [
            {
              "text": "Style: Outlines",
              "type": "text"
            }
          ]
        },
        {
          "type": "paragraph",
          "attrs": {
            "textAlign": "left"
          },
          "content": [
            {
              "text": "Accompanies a solid button to provide additional actions.",
              "type": "text"
            }
          ]
        }
      ]
    }
  },
  "blockType": "text-editor"
}
